flutter_debugger/__init__.py
flutterremotedebugger-0.1.data/scripts/flutterdebugger
flutterremotedebugger-0.1.dist-info/LICENSE
flutterremotedebugger-0.1.dist-info/METADATA
flutterremotedebugger-0.1.dist-info/WHEEL
flutterremotedebugger-0.1.dist-info/top_level.txt
flutterremotedebugger-0.1.dist-info/RECORD
