Metadata-Version: 2.1
Name: flutterremotedebugger
Version: 0.1
Summary: debug flutter in host app
Home-page: https://github.com/SquarePants1991/flutterdebugger
Author: ocean wang
Author-email: tomcat1991@126.com
License: UNKNOWN
Platform: UNKNOWN
Classifier: Programming Language :: Python :: 3
Classifier: License :: OSI Approved :: MIT License
Classifier: Operating System :: OS Independent
